CHANGES.rst
COPYING
MANIFEST.in
README.rst
TEMPLATE_LICENCE.rst
azure-pipelines.yml
pyproject.toml
setup.cfg
setup.py
conda-forge-recipe/meta.yaml
pycraf_gui/__init__.py
pycraf_gui/__main__.py
pycraf_gui/conftest.py
pycraf_gui/init_testrunner.py
pycraf_gui/version.py
pycraf_gui.egg-info/PKG-INFO
pycraf_gui.egg-info/SOURCES.txt
pycraf_gui.egg-info/dependency_links.txt
pycraf_gui.egg-info/entry_points.txt
pycraf_gui.egg-info/not-zip-safe
pycraf_gui.egg-info/requires.txt
pycraf_gui.egg-info/top_level.txt
pycraf_gui/gui/__init__.py
pycraf_gui/gui/gui.py
pycraf_gui/gui/helpers.py
pycraf_gui/gui/plot_widget.py
pycraf_gui/gui/workers.py
pycraf_gui/gui/resources/__init__.py
pycraf_gui/gui/resources/busy_indicator.gif
pycraf_gui/gui/resources/compileform.sh
pycraf_gui/gui/resources/main_form.py
pycraf_gui/gui/resources/main_form.ui
pycraf_gui/gui/resources/resources.qrc
pycraf_gui/gui/resources/resources_rc.py
pycraf_gui/gui/tests/__init__.py
pycraf_gui/gui/tests/test_gui.py