Metadata-Version: 2.1
Name: pycraf-gui
Version: 2.0.1
Summary: pycraf-gui - simple GUI for pycraf
Home-page: https://github.com/bwinkel/pycraf-gui
Author: Benjamin Winkel
Author-email: bwinkel@mpifr.de
License: GPL v3
Project-URL: Documentation, https://bwinkel.github.io/pycraf/latest/gui
Project-URL: Source, https://github.com/bwinkel/pycraf-gui
Keywords: astronomy,astrophysics,radio astronomy,spectrum management,compatibility studies
Classifier: Intended Audience :: Science/Research
Classifier: License :: OSI Approved :: GNU General Public License v3 (GPLv3)
Classifier: Operating System :: OS Independent
Classifier: Programming Language :: C
Classifier: Programming Language :: Cython
Classifier: Programming Language :: Python :: 3
Classifier: Programming Language :: Python :: Implementation :: CPython
Classifier: Topic :: Scientific/Engineering :: Astronomy
Classifier: Topic :: Scientific/Engineering :: Physics
Classifier: Topic :: Scientific/Engineering :: GIS
Requires-Python: >=3.8
Provides-Extra: test
Provides-Extra: recommended
Provides-Extra: all
License-File: COPYING
